{"type":"FeatureCollection","features":[{"type":"Feature","properties":{"name":"Fort Foote","url":"https://www.nps.gov/fofo/index.htm","image":"https://www.nps.gov/fofo/learn/historyculture/images/Image10.jpg","alt":"Cannons at Fort Foote Park","m_color":"#000000","m_size":"medium","m_symbol":"interpretive exhibit"},"geometry":{"type":"Point","coordinates":[-77.02553775099994,38.76692348100005]}}]}