{"type":"FeatureCollection","features":[{"type":"Feature","properties":{"name":"Farmington Landing","url":"https://www.nps.gov/pisc/index.htm","image":"https://npgallery.nps.gov/GetAsset/30C9BE4C-1DD8-B71C-07BE51EA2EC8B333/proxylores.jpg","alt":"Accokeek shorline, looking west from boardwalk","m_color":"#000000","m_size":"medium","m_symbol":"fishing"},"geometry":{"type":"Point","coordinates":[-77.01386626099998,38.69458254400007]}}]}